configbee/__init__.py
configbee/py.typed
configbee/serversdk/__init__.py
configbee/serversdk/_client.py
configbee/serversdk/_client_config.py
configbee/serversdk/py.typed
configbee_server_sdk-0.0.1a1.dist-info/METADATA
configbee_server_sdk-0.0.1a1.dist-info/WHEEL
configbee_server_sdk-0.0.1a1.dist-info/licenses/LICENSE
configbee_server_sdk-0.0.1a1.dist-info/RECORD
