Metadata-Version: 2.4
Name: configbee-server-sdk
Version: 0.0.1a1
Summary: ConfigBee Server Side SDK for Python
Project-URL: Homepage, https://github.com/configbee/cb-server-sdk-python
Author-email: ConfigBee <oss-maintainers@configbee.com>
License-Expression: Apache-2.0
License-File: LICENSE
Classifier: Development Status :: 3 - Alpha
Classifier: Intended Audience :: Developers
Classifier: License :: OSI Approved :: Apache Software License
Classifier: Operating System :: OS Independent
Classifier: Programming Language :: Python
Classifier: Programming Language :: Python :: 3
Classifier: Programming Language :: Python :: 3.10
Classifier: Programming Language :: Python :: 3.11
Classifier: Programming Language :: Python :: 3.12
Classifier: Programming Language :: Python :: 3.13
Classifier: Topic :: Software Development
Requires-Python: >=3.10
Requires-Dist: hishel>=0.1.2
Requires-Dist: httpx-sse>=0.4.1
Requires-Dist: httpx>=0.28.1
